{
  "version": "7",
  "dialect": "sqlite",
  "entries": [
    {
      "idx": 0,
      "version": "6",
      "when": 1751377207974,
      "tag": "0000_lonely_baron_zemo",
      "breakpoints": true
    },
    {
      "idx": 1,
      "version": "6",
      "when": 1751456525285,
      "tag": "0001_last_triton",
      "breakpoints": true
    },
    {
      "idx": 2,
      "version": "6",
      "when": 1751628327887,
      "tag": "0002_orange_post",
      "breakpoints": true
    },
    {
      "idx": 3,
      "version": "6",
      "when": 1751891763061,
      "tag": "0003_massive_kulan_gath",
      "breakpoints": true
    },
    {
      "idx": 4,
      "version": "6",
      "when": 1751895549811,
      "tag": "0004_boring_moon_knight",
      "breakpoints": true
    },
    {
      "idx": 5,
      "version": "6",
      "when": 1751898958222,
      "tag": "0005_fast_reptil",
      "breakpoints": true
    },
    {
      "idx": 6,
      "version": "6",
      "when": 1751919892604,
      "tag": "0006_magenta_infant_terrible",
      "breakpoints": true
    }
  ]
}